[
    {
      "filename": "Fix-1.7.10-v6.jar",
      "size": 16830,
      "MD5": "067F995D78AA5383519B9FE4744F274C"
    },
    {
      "filename": "BetterBuildersWands-0.8.1-1.7.10r92+aec06c3.jar",
      "size": 59896,
      "MD5": "8D0A13692C63A174A100F2DDB6CD0FD8"
    },
    {
      "filename": "BiomesOPlenty-1.7.10-2.1.0.2308-universal.jar",
      "size": 5755198,
      "MD5": "08D7FFBCE53615CB516CB4D1916EECB5"
    },
    {
      "filename": "ClimateControl-0.8.2.jar",
      "size": 389974,
      "MD5": "D0886B4D772556AA55903205A484B79B"
    },
    {
      "filename": "CodeChickenCore-1.7.10-1.0.7.48-universal.jar",
      "size": 143985,
      "MD5": "9624DB3D835155A1BE4BAEF23B7CEE31"
    },
    {
      "filename": "Controlling-1.7.10-1.0.0.4.jar",
      "size": 30090,
      "MD5": "7D8177B009D4A4E4D8C6E425DAFEC43B"
    },
    {
      "filename": "ForgeAuth-0.6.2-1.7.10.jar",
      "size": 26945,
      "MD5": "8F8E7E8115585F7F930E326A36DCEA30"
    },
    {
      "filename": "HBM-NTM-[1.0.27_X5336].jar",
      "size": 52177299,
      "MD5": "B283B63B2FDA2B4C85118C955C9CBB1A"
    },
    {
      "filename": "mw_2.0-0.4.2.5_1.7.10_Patched.jar",
      "size": 24634334,
      "MD5": "C65A6E0EBAC9F0E85E63D4CC24758758"
    },
    {
      "filename": "NotEnoughItems-1.7.10-1.0.5.120-universal.jar",
      "size": 513136,
      "MD5": "742E865A9A80071E80976FFEDC05700E"
    },
    {
      "filename": "OptiFine_1.7.10_HD_U_E7.jar",
      "size": 1774165,
      "MD5": "445062F5AAF982C36C72D90530C26850"
    },
    {
      "filename": "ProjectE-1.7.10-PE1.10.1.jar",
      "size": 1380486,
      "MD5": "850A5BB358E8DCEA14310064FB36B587"
    },
    {
      "filename": "RTG-1.7.10-1.1.1.7.jar",
      "size": 2444070,
      "MD5": "879E4B69150D841132A1035B022AF7BB"
    },
    {
      "filename": "SlashBlade-mc1.7.10-r88.jar",
      "size": 3217649,
      "MD5": "39A5C8ECC1EF778C0A1D033385CA5F4A"
    },
    {
      "filename": "VeinMiner-1.7.10-0.36.0.496+28a7f13.jar",
      "size": 119475,
      "MD5": "CD3E66B31317602E73DD828080AE08DD"
    },
    {
      "filename": "XaerosWorldMap_1.14.1.33_Forge_1.7.10.jar",
      "size": 429095,
      "MD5": "D37BD64CF8182F896E1DCC0D197EDFFF"
    }
  ]